felucca_package_example/__init__.py
felucca_package_example/contract.cairo
felucca_package_example-0.1.3.dist-info/WHEEL
felucca_package_example-0.1.3.dist-info/METADATA
felucca_package_example-0.1.3.dist-info/RECORD
